specialist.py
specialist-0.7.0.dist-info/LICENSE.md
specialist-0.7.0.dist-info/METADATA
specialist-0.7.0.dist-info/WHEEL
specialist-0.7.0.dist-info/entry_points.txt
specialist-0.7.0.dist-info/top_level.txt
specialist-0.7.0.dist-info/RECORD
