Metadata-Version: 2.1
Name: specialist
Version: 0.7.0
Summary: Visualize CPython's specializing, adaptive interpreter.
Home-page: https://github.com/brandtbucher/specialist
Author: Brandt Bucher
Author-email: brandt@python.org
License: MIT
Requires-Python: >=3.11
License-File: LICENSE.md
